q2_clawback/__init__.py
q2_clawback/_clawback.py
q2_clawback/_format.py
q2_clawback/_knn.py
q2_clawback/_transformer.py
q2_clawback/_type.py
q2_clawback/_version.py
q2_clawback/citations.bib
q2_clawback/plugin_setup.py
q2_clawback/assets/index.html
q2_clawback/tests/__init__.py
q2_clawback/tests/test_clawback.py
q2_clawback/tests/data/se-dna-sequences.fasta
q2_clawback/tests/data/taxonomy.tsv
q2_clawback-0.0.3.dist-info/METADATA
q2_clawback-0.0.3.dist-info/RECORD
q2_clawback-0.0.3.dist-info/WHEEL
q2_clawback-0.0.3.dist-info/entry_points.txt
q2_clawback-0.0.3.dist-info/top_level.txt
